django_group_by/__init__.py
django_group_by/group.py
django_group_by/iterable.py
django_group_by/mixin.py
django_group_by/queryset.py
django_group_by-0.3.1.dist-info/DESCRIPTION.rst
django_group_by-0.3.1.dist-info/METADATA
django_group_by-0.3.1.dist-info/RECORD
django_group_by-0.3.1.dist-info/WHEEL
django_group_by-0.3.1.dist-info/metadata.json
django_group_by-0.3.1.dist-info/top_level.txt
