Metadata-Version: 1.1
Name: django-group-by
Version: 0.3.1
Summary: Group by arbitrary model fields
Home-page: https://github.com/kako-nawao/django-group-by
Author: Claudio Omar Melendrez Baeza
Author-email: claudio.melendrez@gmail.com
License: MIT
Keywords: django grouping values models
Platform: UNKNOWN
Classifier: Development Status :: 4 - Beta
Classifier: Environment :: Plugins
Classifier: Framework :: Django :: 1.8
Classifier: Framework :: Django :: 1.9
Classifier: Framework :: Django :: 1.10
Classifier: Intended Audience :: Developers
Classifier: License :: OSI Approved :: MIT License
Classifier: Operating System :: OS Independent
Classifier: Programming Language :: Python :: 2.7
Classifier: Programming Language :: Python :: 3.4
Classifier: Programming Language :: Python :: 3.5
Classifier: Programming Language :: Python :: 3.6
Classifier: Topic :: Software Development
